{
  "experiment": "e6_physics_guided_attention",
  "method": "epgt_v1",
  "config": {
    "data_config": "configs/data/e1_clean_transformer.yaml",
    "model_config": "configs/model/pgt/epgt_v1_mask_only.yaml",
    "architecture": "epgt_v1",
    "model": {
      "d_model": 32,
      "nhead": 4,
      "num_layers": 1,
      "dim_feedforward": 64,
      "dropout": 0.0,
      "max_rel_delay_s": 3e-06,
      "max_doppler_hz": 200.0,
      "max_total_delay_s": 1e-06,
      "max_cfo_hz": 500.0,
      "max_rx_time_offset_s": 2e-07
    },
    "physics": {
      "use_cross_attention_bias": false,
      "use_reliability_mask": true,
      "center_residual_doppler": true,
      "bias_scale": 1.0,
      "bias_eps": 1e-06,
      "symbol_period_s": 0.001,
      "subcarrier_spacing_hz": 15000.0,
      "min_reliability": 0.5
    },
    "l_eff": 12
  },
  "history": [
    {
      "step": 0,
      "train_loss": 0.49613621830940247,
      "param_loss": 0.49613621830940247,
      "tau0_loss": 0.2352788746356964,
      "cfo_loss": 0.010466654784977436,
      "delay_loss": 0.19089822471141815,
      "doppler_loss": 0.023274540901184082,
      "rx_offset_loss": 0.036217931658029556,
      "channel_nmse": 748436.6875,
      "channel_nmse_db": 58.741550679625064,
      "observed_symbol_nmse": 0.01245711836963892,
      "observed_symbol_nmse_db": -19.04582408757698,
      "val_channel_nmse": 748436.6875,
      "val_channel_nmse_db": 58.741550679625064,
      "val_observed_symbol_nmse": 0.01245711836963892,
      "val_observed_symbol_nmse_db": -19.04582408757698
    },
    {
      "step": 1,
      "train_loss": 0.4158899188041687,
      "param_loss": 0.4158899188041687,
      "tau0_loss": 0.17145688831806183,
      "cfo_loss": 0.00858707819133997,
      "delay_loss": 0.1861555576324463,
      "doppler_loss": 0.01747884787619114,
      "rx_offset_loss": 0.032211557030677795
    },
    {
      "step": 2,
      "train_loss": 0.3954664468765259,
      "param_loss": 0.3954664468765259,
      "tau0_loss": 0.1766309142112732,
      "cfo_loss": 0.0047060768119990826,
      "delay_loss": 0.18234173953533173,
      "doppler_loss": 0.011775149963796139,
      "rx_offset_loss": 0.020012587308883667
    },
    {
      "step": 3,
      "train_loss": 0.33872219920158386,
      "param_loss": 0.33872219920158386,
      "tau0_loss": 0.12396668642759323,
      "cfo_loss": 0.0018355438951402903,
      "delay_loss": 0.17810194194316864,
      "doppler_loss": 0.011208750307559967,
      "rx_offset_loss": 0.023609288036823273
    },
    {
      "step": 4,
      "train_loss": 0.33099833130836487,
      "param_loss": 0.33099833130836487,
      "tau0_loss": 0.12982423603534698,
      "cfo_loss": 0.0018282165983691812,
      "delay_loss": 0.17393581569194794,
      "doppler_loss": 0.006824298296123743,
      "rx_offset_loss": 0.018585773184895515,
      "channel_nmse": 130921.5703125,
      "channel_nmse_db": 51.1701120572521,
      "observed_symbol_nmse": 0.004092334304004908,
      "observed_symbol_nmse_db": -23.880288957593528,
      "val_channel_nmse": 130921.5703125,
      "val_channel_nmse_db": 51.1701120572521,
      "val_observed_symbol_nmse": 0.004092334304004908,
      "val_observed_symbol_nmse_db": -23.880288957593528
    },
    {
      "step": 5,
      "train_loss": 0.28683748841285706,
      "param_loss": 0.28683748841285706,
      "tau0_loss": 0.08696627616882324,
      "cfo_loss": 0.0013140215305611491,
      "delay_loss": 0.16932813823223114,
      "doppler_loss": 0.007236156612634659,
      "rx_offset_loss": 0.021992890164256096
    },
    {
      "step": 6,
      "train_loss": 0.28318679332733154,
      "param_loss": 0.28318679332733154,
      "tau0_loss": 0.09481581300497055,
      "cfo_loss": 0.0011664130724966526,
      "delay_loss": 0.16495101153850555,
      "doppler_loss": 0.004746844992041588,
      "rx_offset_loss": 0.017506716772913933
    },
    {
      "step": 7,
      "train_loss": 0.249330535531044,
      "param_loss": 0.249330535531044,
      "tau0_loss": 0.06119171902537346,
      "cfo_loss": 0.0012146875960752368,
      "delay_loss": 0.16015879809856415,
      "doppler_loss": 0.00575247360393405,
      "rx_offset_loss": 0.02101285196840763
    },
    {
      "step": 8,
      "train_loss": 0.2501491904258728,
      "param_loss": 0.2501491904258728,
      "tau0_loss": 0.07080510258674622,
      "cfo_loss": 0.0017321788473054767,
      "delay_loss": 0.155711829662323,
      "doppler_loss": 0.004886845592409372,
      "rx_offset_loss": 0.017013251781463623
    },
    {
      "step": 9,
      "train_loss": 0.2224435955286026,
      "param_loss": 0.2224435955286026,
      "tau0_loss": 0.04423043131828308,
      "cfo_loss": 0.0010230833431705832,
      "delay_loss": 0.15083526074886322,
      "doppler_loss": 0.005533570423722267,
      "rx_offset_loss": 0.02082124352455139,
      "channel_nmse": 30524.546875,
      "channel_nmse_db": 44.84649225732474,
      "observed_symbol_nmse": 0.0012986877700313926,
      "observed_symbol_nmse_db": -28.864952489401855,
      "val_channel_nmse": 30524.546875,
      "val_channel_nmse_db": 44.84649225732474,
      "val_observed_symbol_nmse": 0.0012986877700313926,
      "val_observed_symbol_nmse_db": -28.864952489401855
    },
    {
      "step": 10,
      "train_loss": 0.22286856174468994,
      "param_loss": 0.22286856174468994,
      "tau0_loss": 0.05430134758353233,
      "cfo_loss": 0.0007979648071341217,
      "delay_loss": 0.14628051221370697,
      "doppler_loss": 0.005067966412752867,
      "rx_offset_loss": 0.01642078533768654
    },
    {
      "step": 11,
      "train_loss": 0.1999390870332718,
      "param_loss": 0.1999390870332718,
      "tau0_loss": 0.0325600802898407,
      "cfo_loss": 0.0006879041902720928,
      "delay_loss": 0.1414380669593811,
      "doppler_loss": 0.005076936911791563,
      "rx_offset_loss": 0.02017611637711525
    },
    {
      "step": 12,
      "train_loss": 0.19947189092636108,
      "param_loss": 0.19947189092636108,
      "tau0_loss": 0.041998930275440216,
      "cfo_loss": 0.0005568451597355306,
      "delay_loss": 0.1367216855287552,
      "doppler_loss": 0.004584708716720343,
      "rx_offset_loss": 0.015609714202582836
    },
    {
      "step": 13,
      "train_loss": 0.18011821806430817,
      "param_loss": 0.18011821806430817,
      "tau0_loss": 0.02390177734196186,
      "cfo_loss": 0.0007795142009854317,
      "delay_loss": 0.13189823925495148,
      "doppler_loss": 0.004178378265351057,
      "rx_offset_loss": 0.019360322505235672
    },
    {
      "step": 14,
      "train_loss": 0.17839254438877106,
      "param_loss": 0.17839254438877106,
      "tau0_loss": 0.03231555223464966,
      "cfo_loss": 0.0004096442717127502,
      "delay_loss": 0.12693794071674347,
      "doppler_loss": 0.0035792095586657524,
      "rx_offset_loss": 0.01515018567442894,
      "channel_nmse": 2403.612060546875,
      "channel_nmse_db": 33.80864374495726,
      "observed_symbol_nmse": 0.00038066363777033985,
      "observed_symbol_nmse_db": -34.19458605285919,
      "val_channel_nmse": 2403.612060546875,
      "val_channel_nmse_db": 33.80864374495726,
      "val_observed_symbol_nmse": 0.00038066363777033985,
      "val_observed_symbol_nmse_db": -34.19458605285919
    },
    {
      "step": 15,
      "train_loss": 0.1611853539943695,
      "param_loss": 0.1611853539943695,
      "tau0_loss": 0.01733369007706642,
      "cfo_loss": 0.0003573696594685316,
      "delay_loss": 0.12206251174211502,
      "doppler_loss": 0.0029836727771908045,
      "rx_offset_loss": 0.0184481181204319
    },
    {
      "step": 16,
      "train_loss": 0.15952083468437195,
      "param_loss": 0.15952083468437195,
      "tau0_loss": 0.024745170027017593,
      "cfo_loss": 0.0006622166838496923,
      "delay_loss": 0.11682078242301941,
      "doppler_loss": 0.002398233860731125,
      "rx_offset_loss": 0.014894422143697739
    },
    {
      "step": 17,
      "train_loss": 0.14422622323036194,
      "param_loss": 0.14422622323036194,
      "tau0_loss": 0.01251174882054329,
      "cfo_loss": 0.00047107727732509375,
      "delay_loss": 0.11182475090026855,
      "doppler_loss": 0.0018618666799739003,
      "rx_offset_loss": 0.01755678467452526
    },
    {
      "step": 18,
      "train_loss": 0.14223596453666687,
      "param_loss": 0.14223596453666687,
      "tau0_loss": 0.0190373957157135,
      "cfo_loss": 0.0005939131369814277,
      "delay_loss": 0.10636364668607712,
      "doppler_loss": 0.0014835543697699904,
      "rx_offset_loss": 0.014757456257939339
    },
    {
      "step": 19,
      "train_loss": 0.12870079278945923,
      "param_loss": 0.12870079278945923,
      "tau0_loss": 0.009099828079342842,
      "cfo_loss": 0.00020425941329449415,
      "delay_loss": 0.10128024965524673,
      "doppler_loss": 0.0011637408751994371,
      "rx_offset_loss": 0.016952719539403915,
      "channel_nmse": 21.700193405151367,
      "channel_nmse_db": 13.364636045589506,
      "observed_symbol_nmse": 6.110288086347282e-05,
      "observed_symbol_nmse_db": -42.139383061586145,
      "val_channel_nmse": 21.700193405151367,
      "val_channel_nmse_db": 13.364636045589506,
      "val_observed_symbol_nmse": 6.110288086347282e-05,
      "val_observed_symbol_nmse_db": -42.139383061586145
    },
    {
      "step": 20,
      "train_loss": 0.1264670044183731,
      "param_loss": 0.1264670044183731,
      "tau0_loss": 0.01478089950978756,
      "cfo_loss": 0.00021062558516860008,
      "delay_loss": 0.09572746604681015,
      "doppler_loss": 0.0010637551313266158,
      "rx_offset_loss": 0.014684254303574562
    },
    {
      "step": 21,
      "train_loss": 0.11527419835329056,
      "param_loss": 0.11527419835329056,
      "tau0_loss": 0.006690266542136669,
      "cfo_loss": 0.0003179831837769598,
      "delay_loss": 0.09062362462282181,
      "doppler_loss": 0.0009542244370095432,
      "rx_offset_loss": 0.01668809913098812
    },
    {
      "step": 22,
      "train_loss": 0.11256082355976105,
      "param_loss": 0.11256082355976105,
      "tau0_loss": 0.011543083004653454,
      "cfo_loss": 0.0002713317226152867,
      "delay_loss": 0.08510927110910416,
      "doppler_loss": 0.001024549943394959,
      "rx_offset_loss": 0.014612581580877304
    },
    {
      "step": 23,
      "train_loss": 0.10282304883003235,
      "param_loss": 0.10282304883003235,
      "tau0_loss": 0.004989412147551775,
      "cfo_loss": 0.00019983804668299854,
      "delay_loss": 0.08004333823919296,
      "doppler_loss": 0.0009814377408474684,
      "rx_offset_loss": 0.016609027981758118
    },
    {
      "step": 24,
      "train_loss": 0.09930078685283661,
      "param_loss": 0.09930078685283661,
      "tau0_loss": 0.009072238579392433,
      "cfo_loss": 0.0001358416338916868,
      "delay_loss": 0.07467615604400635,
      "doppler_loss": 0.0010157562792301178,
      "rx_offset_loss": 0.014400796964764595,
      "channel_nmse": 1.2281221151351929,
      "channel_nmse_db": 0.8924155189722743,
      "observed_symbol_nmse": 4.634995548258303e-06,
      "observed_symbol_nmse_db": -53.33950584944064,
      "val_channel_nmse": 1.2281221151351929,
      "val_channel_nmse_db": 0.8924155189722743,
      "val_observed_symbol_nmse": 4.634995548258303e-06,
      "val_observed_symbol_nmse_db": -53.33950584944064
    }
  ],
  "final": {
    "step": 24,
    "train_loss": 0.09930078685283661,
    "param_loss": 0.09930078685283661,
    "tau0_loss": 0.009072238579392433,
    "cfo_loss": 0.0001358416338916868,
    "delay_loss": 0.07467615604400635,
    "doppler_loss": 0.0010157562792301178,
    "rx_offset_loss": 0.014400796964764595,
    "channel_nmse": 1.2281221151351929,
    "channel_nmse_db": 0.8924155189722743,
    "observed_symbol_nmse": 4.634995548258303e-06,
    "observed_symbol_nmse_db": -53.33950584944064,
    "val_channel_nmse": 1.2281221151351929,
    "val_channel_nmse_db": 0.8924155189722743,
    "val_observed_symbol_nmse": 4.634995548258303e-06,
    "val_observed_symbol_nmse_db": -53.33950584944064
  },
  "variant": "epgt_v1_mask_only"
}