[
  {
    "experiment": "e6_physics_guided_attention",
    "method": "epgt_v1",
    "variant": "bias_scale_0p0",
    "ablation_param": "bias_scale",
    "ablation_value": 0.0,
    "config": {
      "data_config": "configs/data/e1_clean_transformer.yaml",
      "model_config": "configs\\model\\pgt\\epgt_v1_bias_only.yaml",
      "architecture": "epgt_v1",
      "model": {
        "d_model": 32,
        "nhead": 4,
        "num_layers": 1,
        "dim_feedforward": 64,
        "dropout": 0.0,
        "max_rel_delay_s": 3e-06,
        "max_doppler_hz": 200.0,
        "max_total_delay_s": 1e-06,
        "max_cfo_hz": 500.0,
        "max_rx_time_offset_s": 2e-07
      },
      "physics": {
        "use_cross_attention_bias": true,
        "use_reliability_mask": false,
        "center_residual_doppler": true,
        "bias_scale": 0.0,
        "bias_eps": 1e-06,
        "symbol_period_s": 0.001,
        "subcarrier_spacing_hz": 15000.0
      },
      "l_eff": 12
    },
    "history": [
      {
        "step": 0,
        "train_loss": 0.4334526062011719,
        "param_loss": 0.4334526062011719,
        "tau0_loss": 0.15949590504169464,
        "cfo_loss": 0.00433703837916255,
        "delay_loss": 0.19778931140899658,
        "doppler_loss": 0.033475011587142944,
        "rx_offset_loss": 0.03835533186793327,
        "channel_nmse": 1241894.125,
        "channel_nmse_db": 60.94084572581126,
        "observed_symbol_nmse": 0.00878158863633871,
        "observed_symbol_nmse_db": -20.564269107431514,
        "val_channel_nmse": 1241894.125,
        "val_channel_nmse_db": 60.94084572581126,
        "val_observed_symbol_nmse": 0.00878158863633871,
        "val_observed_symbol_nmse_db": -20.564269107431514
      },
      {
        "step": 1,
        "train_loss": 0.35943037271499634,
        "param_loss": 0.35943037271499634,
        "tau0_loss": 0.10321936756372452,
        "cfo_loss": 0.013738678768277168,
        "delay_loss": 0.1920299082994461,
        "doppler_loss": 0.01953781023621559,
        "rx_offset_loss": 0.0309046171605587
      },
      {
        "step": 2,
        "train_loss": 0.32421958446502686,
        "param_loss": 0.32421958446502686,
        "tau0_loss": 0.10205399990081787,
        "cfo_loss": 0.008607340976595879,
        "delay_loss": 0.18449068069458008,
        "doppler_loss": 0.012184967286884785,
        "rx_offset_loss": 0.01688258722424507
      },
      {
        "step": 3,
        "train_loss": 0.2830517590045929,
        "param_loss": 0.2830517590045929,
        "tau0_loss": 0.0632925033569336,
        "cfo_loss": 0.0066393599845469,
        "delay_loss": 0.17848141491413116,
        "doppler_loss": 0.01045823935419321,
        "rx_offset_loss": 0.024180244654417038
      },
      {
        "step": 4,
        "train_loss": 0.2693808674812317,
        "param_loss": 0.2693808674812317,
        "tau0_loss": 0.06871505081653595,
        "cfo_loss": 0.0018644074443727732,
        "delay_loss": 0.17058831453323364,
        "doppler_loss": 0.009529157541692257,
        "rx_offset_loss": 0.01868394948542118,
        "channel_nmse": 255259.671875,
        "channel_nmse_db": 54.06982206635003,
        "observed_symbol_nmse": 0.003209136426448822,
        "observed_symbol_nmse_db": -24.936118196982733,
        "val_channel_nmse": 255259.671875,
        "val_channel_nmse_db": 54.06982206635003,
        "val_observed_symbol_nmse": 0.003209136426448822,
        "val_observed_symbol_nmse_db": -24.936118196982733
      },
      {
        "step": 5,
        "train_loss": 0.24000480771064758,
        "param_loss": 0.24000480771064758,
        "tau0_loss": 0.040758997201919556,
        "cfo_loss": 0.0016601089155301452,
        "delay_loss": 0.16431312263011932,
        "doppler_loss": 0.010135008953511715,
        "rx_offset_loss": 0.02313757687807083
      },
      {
        "step": 6,
        "train_loss": 0.23502427339553833,
        "param_loss": 0.23502427339553833,
        "tau0_loss": 0.0480627566576004,
        "cfo_loss": 0.0014481652760878205,
        "delay_loss": 0.15704017877578735,
        "doppler_loss": 0.010333017446100712,
        "rx_offset_loss": 0.01814015582203865
      },
      {
        "step": 7,
        "train_loss": 0.20971885323524475,
        "param_loss": 0.20971885323524475,
        "tau0_loss": 0.02644478529691696,
        "cfo_loss": 0.0013007385423406959,
        "delay_loss": 0.15089289844036102,
        "doppler_loss": 0.01043171901255846,
        "rx_offset_loss": 0.020648695528507233
      },
      {
        "step": 8,
        "train_loss": 0.20525118708610535,
        "param_loss": 0.20525118708610535,
        "tau0_loss": 0.03363804891705513,
        "cfo_loss": 0.0010060782078653574,
        "delay_loss": 0.14447049796581268,
        "doppler_loss": 0.010200552642345428,
        "rx_offset_loss": 0.01593601331114769
      },
      {
        "step": 9,
        "train_loss": 0.1859491765499115,
        "param_loss": 0.1859491765499115,
        "tau0_loss": 0.01697596348822117,
        "cfo_loss": 0.001372819533571601,
        "delay_loss": 0.1386110633611679,
        "doppler_loss": 0.00942430179566145,
        "rx_offset_loss": 0.019565025344491005,
        "channel_nmse": 87515.375,
        "channel_nmse_db": 49.42084358063244,
        "observed_symbol_nmse": 0.0008732385467737913,
        "observed_symbol_nmse_db": -30.58867101277217,
        "val_channel_nmse": 87515.375,
        "val_channel_nmse_db": 49.42084358063244,
        "val_observed_symbol_nmse": 0.0008732385467737913,
        "val_observed_symbol_nmse_db": -30.58867101277217
      },
      {
        "step": 10,
        "train_loss": 0.1804642677307129,
        "param_loss": 0.1804642677307129,
        "tau0_loss": 0.023492595180869102,
        "cfo_loss": 0.0010613154154270887,
        "delay_loss": 0.13276812434196472,
        "doppler_loss": 0.008462011814117432,
        "rx_offset_loss": 0.014680219814181328
      },
      {
        "step": 11,
        "train_loss": 0.16638143360614777,
        "param_loss": 0.16638143360614777,
        "tau0_loss": 0.01093222200870514,
        "cfo_loss": 0.0010483916848897934,
        "delay_loss": 0.12711140513420105,
        "doppler_loss": 0.007334078196436167,
        "rx_offset_loss": 0.019955338910222054
      },
      {
        "step": 12,
        "train_loss": 0.15922927856445312,
        "param_loss": 0.15922927856445312,
        "tau0_loss": 0.01655193231999874,
        "cfo_loss": 0.0006887201452627778,
        "delay_loss": 0.12128868699073792,
        "doppler_loss": 0.006098777521401644,
        "rx_offset_loss": 0.014601148664951324
      },
      {
        "step": 13,
        "train_loss": 0.148148775100708,
        "param_loss": 0.148148775100708,
        "tau0_loss": 0.007168217096477747,
        "cfo_loss": 0.0007302058511413634,
        "delay_loss": 0.11542195081710815,
        "doppler_loss": 0.0051466007716953754,
        "rx_offset_loss": 0.019681794568896294
      },
      {
        "step": 14,
        "train_loss": 0.13982774317264557,
        "param_loss": 0.13982774317264557,
        "tau0_loss": 0.011813566088676453,
        "cfo_loss": 0.0005922109121456742,
        "delay_loss": 0.10911455005407333,
        "doppler_loss": 0.003983821254223585,
        "rx_offset_loss": 0.01432359404861927,
        "channel_nmse": 523.9439086914062,
        "channel_nmse_db": 27.192847956674914,
        "observed_symbol_nmse": 0.00012644100934267044,
        "observed_symbol_nmse_db": -38.98112042534344,
        "val_channel_nmse": 523.9439086914062,
        "val_channel_nmse_db": 27.192847956674914,
        "val_observed_symbol_nmse": 0.00012644100934267044,
        "val_observed_symbol_nmse_db": -38.98112042534344
      },
      {
        "step": 15,
        "train_loss": 0.12976796925067902,
        "param_loss": 0.12976796925067902,
        "tau0_loss": 0.004903814289718866,
        "cfo_loss": 0.0006136781885288656,
        "delay_loss": 0.10279890894889832,
        "doppler_loss": 0.0033260593190789223,
        "rx_offset_loss": 0.01812550611793995
      },
      {
        "step": 16,
        "train_loss": 0.12219037860631943,
        "param_loss": 0.12219037860631943,
        "tau0_loss": 0.008693180046975613,
        "cfo_loss": 0.0005040985415689647,
        "delay_loss": 0.096018947660923,
        "doppler_loss": 0.0025116465985774994,
        "rx_offset_loss": 0.014462510123848915
      },
      {
        "step": 17,
        "train_loss": 0.11329437792301178,
        "param_loss": 0.11329437792301178,
        "tau0_loss": 0.0036638048477470875,
        "cfo_loss": 0.0006049948278814554,
        "delay_loss": 0.08941873162984848,
        "doppler_loss": 0.002205316675826907,
        "rx_offset_loss": 0.017401523888111115
      },
      {
        "step": 18,
        "train_loss": 0.10655733942985535,
        "param_loss": 0.10655733942985535,
        "tau0_loss": 0.006736287381500006,
        "cfo_loss": 0.00042582719470374286,
        "delay_loss": 0.08247378468513489,
        "doppler_loss": 0.001812244183383882,
        "rx_offset_loss": 0.015109199099242687
      },
      {
        "step": 19,
        "train_loss": 0.09832903742790222,
        "param_loss": 0.09832903742790222,
        "tau0_loss": 0.003030943451449275,
        "cfo_loss": 0.0004348147485870868,
        "delay_loss": 0.07590823620557785,
        "doppler_loss": 0.0017870540032163262,
        "rx_offset_loss": 0.017167996615171432,
        "channel_nmse": 144.52093505859375,
        "channel_nmse_db": 21.599307628148487,
        "observed_symbol_nmse": 1.5634614101145416e-05,
        "observed_symbol_nmse_db": -48.0591280591489,
        "val_channel_nmse": 144.52093505859375,
        "val_channel_nmse_db": 21.599307628148487,
        "val_observed_symbol_nmse": 1.5634614101145416e-05,
        "val_observed_symbol_nmse_db": -48.0591280591489
      },
      {
        "step": 20,
        "train_loss": 0.09140332788228989,
        "param_loss": 0.09140332788228989,
        "tau0_loss": 0.005471737124025822,
        "cfo_loss": 0.00040378107223659754,
        "delay_loss": 0.06913737207651138,
        "doppler_loss": 0.001729575335048139,
        "rx_offset_loss": 0.014660854823887348
      },
      {
        "step": 21,
        "train_loss": 0.08459492027759552,
        "param_loss": 0.08459492027759552,
        "tau0_loss": 0.0027055973187088966,
        "cfo_loss": 0.00039501453284174204,
        "delay_loss": 0.06290628761053085,
        "doppler_loss": 0.0017595668323338032,
        "rx_offset_loss": 0.01682845689356327
      },
      {
        "step": 22,
        "train_loss": 0.07710578292608261,
        "param_loss": 0.07710578292608261,
        "tau0_loss": 0.00457750866189599,
        "cfo_loss": 0.0003047569771297276,
        "delay_loss": 0.056599248200654984,
        "doppler_loss": 0.0016524881357327104,
        "rx_offset_loss": 0.013971785083413124
      },
      {
        "step": 23,
        "train_loss": 0.07231595367193222,
        "param_loss": 0.07231595367193222,
        "tau0_loss": 0.0025564900133758783,
        "cfo_loss": 0.00033371002064086497,
        "delay_loss": 0.050924986600875854,
        "doppler_loss": 0.0015592275885865092,
        "rx_offset_loss": 0.01694153994321823
      },
      {
        "step": 24,
        "train_loss": 0.06470601260662079,
        "param_loss": 0.06470601260662079,
        "tau0_loss": 0.003962712828069925,
        "cfo_loss": 0.00030960061121731997,
        "delay_loss": 0.04524235427379608,
        "doppler_loss": 0.0013538423227146268,
        "rx_offset_loss": 0.01383750606328249,
        "channel_nmse": 1.963788390159607,
        "channel_nmse_db": 2.930946881674151,
        "observed_symbol_nmse": 8.222552310144238e-07,
        "observed_symbol_nmse_db": -60.84992826772122,
        "val_channel_nmse": 1.963788390159607,
        "val_channel_nmse_db": 2.930946881674151,
        "val_observed_symbol_nmse": 8.222552310144238e-07,
        "val_observed_symbol_nmse_db": -60.84992826772122
      }
    ],
    "final": {
      "step": 24,
      "train_loss": 0.06470601260662079,
      "param_loss": 0.06470601260662079,
      "tau0_loss": 0.003962712828069925,
      "cfo_loss": 0.00030960061121731997,
      "delay_loss": 0.04524235427379608,
      "doppler_loss": 0.0013538423227146268,
      "rx_offset_loss": 0.01383750606328249,
      "channel_nmse": 1.963788390159607,
      "channel_nmse_db": 2.930946881674151,
      "observed_symbol_nmse": 8.222552310144238e-07,
      "observed_symbol_nmse_db": -60.84992826772122,
      "val_channel_nmse": 1.963788390159607,
      "val_channel_nmse_db": 2.930946881674151,
      "val_observed_symbol_nmse": 8.222552310144238e-07,
      "val_observed_symbol_nmse_db": -60.84992826772122
    }
  },
  {
    "experiment": "e6_physics_guided_attention",
    "method": "epgt_v1",
    "variant": "bias_scale_0p25",
    "ablation_param": "bias_scale",
    "ablation_value": 0.25,
    "config": {
      "data_config": "configs/data/e1_clean_transformer.yaml",
      "model_config": "configs\\model\\pgt\\epgt_v1_bias_only.yaml",
      "architecture": "epgt_v1",
      "model": {
        "d_model": 32,
        "nhead": 4,
        "num_layers": 1,
        "dim_feedforward": 64,
        "dropout": 0.0,
        "max_rel_delay_s": 3e-06,
        "max_doppler_hz": 200.0,
        "max_total_delay_s": 1e-06,
        "max_cfo_hz": 500.0,
        "max_rx_time_offset_s": 2e-07
      },
      "physics": {
        "use_cross_attention_bias": true,
        "use_reliability_mask": false,
        "center_residual_doppler": true,
        "bias_scale": 0.25,
        "bias_eps": 1e-06,
        "symbol_period_s": 0.001,
        "subcarrier_spacing_hz": 15000.0
      },
      "l_eff": 12
    },
    "history": [
      {
        "step": 0,
        "train_loss": 0.4436386227607727,
        "param_loss": 0.4436386227607727,
        "tau0_loss": 0.12573882937431335,
        "cfo_loss": 0.03961791470646858,
        "delay_loss": 0.18802650272846222,
        "doppler_loss": 0.04290914535522461,
        "rx_offset_loss": 0.047346241772174835,
        "channel_nmse": 16245744.0,
        "channel_nmse_db": 72.10739605351401,
        "observed_symbol_nmse": 0.018555570393800735,
        "observed_symbol_nmse_db": -17.31525690977984,
        "val_channel_nmse": 16245744.0,
        "val_channel_nmse_db": 72.10739605351401,
        "val_observed_symbol_nmse": 0.018555570393800735,
        "val_observed_symbol_nmse_db": -17.31525690977984
      },
      {
        "step": 1,
        "train_loss": 0.35441792011260986,
        "param_loss": 0.35441792011260986,
        "tau0_loss": 0.09469762444496155,
        "cfo_loss": 0.0036625920329242945,
        "delay_loss": 0.18085826933383942,
        "doppler_loss": 0.026648765429854393,
        "rx_offset_loss": 0.04855066537857056
      },
      {
        "step": 2,
        "train_loss": 0.3319231867790222,
        "param_loss": 0.3319231867790222,
        "tau0_loss": 0.1049073338508606,
        "cfo_loss": 0.0035784561187028885,
        "delay_loss": 0.17550726234912872,
        "doppler_loss": 0.016345908865332603,
        "rx_offset_loss": 0.03158419206738472
      },
      {
        "step": 3,
        "train_loss": 0.2870042622089386,
        "param_loss": 0.2870042622089386,
        "tau0_loss": 0.07051359862089157,
        "cfo_loss": 0.003611210035160184,
        "delay_loss": 0.16892099380493164,
        "doppler_loss": 0.010628185234963894,
        "rx_offset_loss": 0.03333025053143501
      },
      {
        "step": 4,
        "train_loss": 0.27003130316734314,
        "param_loss": 0.27003130316734314,
        "tau0_loss": 0.0788748562335968,
        "cfo_loss": 0.0005751330754719675,
        "delay_loss": 0.16415303945541382,
        "doppler_loss": 0.007233867421746254,
        "rx_offset_loss": 0.01919441856443882,
        "channel_nmse": 180569.953125,
        "channel_nmse_db": 52.56645485303928,
        "observed_symbol_nmse": 0.008741638623178005,
        "observed_symbol_nmse_db": -20.584071510343477,
        "val_channel_nmse": 180569.953125,
        "val_channel_nmse_db": 52.56645485303928,
        "val_observed_symbol_nmse": 0.008741638623178005,
        "val_observed_symbol_nmse_db": -20.584071510343477
      },
      {
        "step": 5,
        "train_loss": 0.24267515540122986,
        "param_loss": 0.24267515540122986,
        "tau0_loss": 0.0509323924779892,
        "cfo_loss": 0.0025096454191952944,
        "delay_loss": 0.15810568630695343,
        "doppler_loss": 0.006273023318499327,
        "rx_offset_loss": 0.024854401126503944
      },
      {
        "step": 6,
        "train_loss": 0.23830334842205048,
        "param_loss": 0.23830334842205048,
        "tau0_loss": 0.059122100472450256,
        "cfo_loss": 0.0042365239933133125,
        "delay_loss": 0.1535326987504959,
        "doppler_loss": 0.0049789659678936005,
        "rx_offset_loss": 0.016433056443929672
      },
      {
        "step": 7,
        "train_loss": 0.21473225951194763,
        "param_loss": 0.21473225951194763,
        "tau0_loss": 0.036233484745025635,
        "cfo_loss": 0.0031794647220522165,
        "delay_loss": 0.1474253535270691,
        "doppler_loss": 0.004793961066752672,
        "rx_offset_loss": 0.02310001105070114
      },
      {
        "step": 8,
        "train_loss": 0.2091427892446518,
        "param_loss": 0.2091427892446518,
        "tau0_loss": 0.04407189413905144,
        "cfo_loss": 0.001705457572825253,
        "delay_loss": 0.14241839945316315,
        "doppler_loss": 0.004030581098049879,
        "rx_offset_loss": 0.01691645011305809
      },
      {
        "step": 9,
        "train_loss": 0.18792076408863068,
        "param_loss": 0.18792076408863068,
        "tau0_loss": 0.025392822921276093,
        "cfo_loss": 0.0005622234893962741,
        "delay_loss": 0.13586781919002533,
        "doppler_loss": 0.0038319185841828585,
        "rx_offset_loss": 0.022265974432229996,
        "channel_nmse": 5968.35400390625,
        "channel_nmse_db": 37.758545747500484,
        "observed_symbol_nmse": 0.0006483581964857876,
        "observed_symbol_nmse_db": -31.881849938026917,
        "val_channel_nmse": 5968.35400390625,
        "val_channel_nmse_db": 37.758545747500484,
        "val_observed_symbol_nmse": 0.0006483581964857876,
        "val_observed_symbol_nmse_db": -31.881849938026917
      },
      {
        "step": 10,
        "train_loss": 0.18276208639144897,
        "param_loss": 0.18276208639144897,
        "tau0_loss": 0.032612621784210205,
        "cfo_loss": 0.00032830340205691755,
        "delay_loss": 0.13030479848384857,
        "doppler_loss": 0.0032750479876995087,
        "rx_offset_loss": 0.016241317614912987
      },
      {
        "step": 11,
        "train_loss": 0.1650458574295044,
        "param_loss": 0.1650458574295044,
        "tau0_loss": 0.017504042014479637,
        "cfo_loss": 0.0015623385552316904,
        "delay_loss": 0.12341292947530746,
        "doppler_loss": 0.002960081212222576,
        "rx_offset_loss": 0.019606448709964752
      },
      {
        "step": 12,
        "train_loss": 0.15955312550067902,
        "param_loss": 0.15955312550067902,
        "tau0_loss": 0.023985764011740685,
        "cfo_loss": 0.0007846558000892401,
        "delay_loss": 0.1174425408244133,
        "doppler_loss": 0.002505311742424965,
        "rx_offset_loss": 0.014834847301244736
      },
      {
        "step": 13,
        "train_loss": 0.14251446723937988,
        "param_loss": 0.14251446723937988,
        "tau0_loss": 0.011974026449024677,
        "cfo_loss": 0.0009286393178626895,
        "delay_loss": 0.11045575141906738,
        "doppler_loss": 0.002211321610957384,
        "rx_offset_loss": 0.016944728791713715
      },
      {
        "step": 14,
        "train_loss": 0.13894599676132202,
        "param_loss": 0.13894599676132202,
        "tau0_loss": 0.017643960192799568,
        "cfo_loss": 0.00016211489855777472,
        "delay_loss": 0.10429694503545761,
        "doppler_loss": 0.00187822210136801,
        "rx_offset_loss": 0.014964747242629528,
        "channel_nmse": 94.0448226928711,
        "channel_nmse_db": 19.73334891988401,
        "observed_symbol_nmse": 5.2518767915898934e-05,
        "observed_symbol_nmse_db": -42.79685462691053,
        "val_channel_nmse": 94.0448226928711,
        "val_channel_nmse_db": 19.73334891988401,
        "val_observed_symbol_nmse": 5.2518767915898934e-05,
        "val_observed_symbol_nmse_db": -42.79685462691053
      },
      {
        "step": 15,
        "train_loss": 0.12404680997133255,
        "param_loss": 0.12404680997133255,
        "tau0_loss": 0.00819573737680912,
        "cfo_loss": 0.00034251913893967867,
        "delay_loss": 0.0973893329501152,
        "doppler_loss": 0.0016994731267914176,
        "rx_offset_loss": 0.016419753432273865
      },
      {
        "step": 16,
        "train_loss": 0.12279371917247772,
        "param_loss": 0.12279371917247772,
        "tau0_loss": 0.013036803342401981,
        "cfo_loss": 0.0008131390786729753,
        "delay_loss": 0.09115582704544067,
        "doppler_loss": 0.001455951016396284,
        "rx_offset_loss": 0.016331996768712997
      },
      {
        "step": 17,
        "train_loss": 0.1091802716255188,
        "param_loss": 0.1091802716255188,
        "tau0_loss": 0.005720428191125393,
        "cfo_loss": 0.0005108708865009248,
        "delay_loss": 0.08444911986589432,
        "doppler_loss": 0.0013590608723461628,
        "rx_offset_loss": 0.017140788957476616
      },
      {
        "step": 18,
        "train_loss": 0.1062505841255188,
        "param_loss": 0.1062505841255188,
        "tau0_loss": 0.009798288345336914,
        "cfo_loss": 0.00044530531158670783,
        "delay_loss": 0.07828660309314728,
        "doppler_loss": 0.001181023777462542,
        "rx_offset_loss": 0.01653936505317688
      },
      {
        "step": 19,
        "train_loss": 0.09491762518882751,
        "param_loss": 0.09491762518882751,
        "tau0_loss": 0.00418876763433218,
        "cfo_loss": 0.0002515246451366693,
        "delay_loss": 0.07192475348711014,
        "doppler_loss": 0.0011335433227941394,
        "rx_offset_loss": 0.017419030889868736,
        "channel_nmse": 2.7004215717315674,
        "channel_nmse_db": 4.314315685980002,
        "observed_symbol_nmse": 4.440254542714683e-06,
        "observed_symbol_nmse_db": -53.52592034931041,
        "val_channel_nmse": 2.7004215717315674,
        "val_channel_nmse_db": 4.314315685980002,
        "val_observed_symbol_nmse": 4.440254542714683e-06,
        "val_observed_symbol_nmse_db": -53.52592034931041
      },
      {
        "step": 20,
        "train_loss": 0.09013509005308151,
        "param_loss": 0.09013509005308151,
        "tau0_loss": 0.0075573064386844635,
        "cfo_loss": 0.0002173633110942319,
        "delay_loss": 0.06599355489015579,
        "doppler_loss": 0.0010461233323439956,
        "rx_offset_loss": 0.01532074250280857
      },
      {
        "step": 21,
        "train_loss": 0.08248384296894073,
        "param_loss": 0.08248384296894073,
        "tau0_loss": 0.0032807381357997656,
        "cfo_loss": 0.0007561543025076389,
        "delay_loss": 0.06011107191443443,
        "doppler_loss": 0.0010443878127261996,
        "rx_offset_loss": 0.017291489988565445
      },
      {
        "step": 22,
        "train_loss": 0.07606884092092514,
        "param_loss": 0.07606884092092514,
        "tau0_loss": 0.006017668172717094,
        "cfo_loss": 0.00029579055262729526,
        "delay_loss": 0.05456291511654854,
        "doppler_loss": 0.001090537989512086,
        "rx_offset_loss": 0.014101928099989891
      },
      {
        "step": 23,
        "train_loss": 0.07062417268753052,
        "param_loss": 0.07062417268753052,
        "tau0_loss": 0.0027782118413597345,
        "cfo_loss": 0.0003381412534508854,
        "delay_loss": 0.049253255128860474,
        "doppler_loss": 0.0011226978385820985,
        "rx_offset_loss": 0.0171318668872118
      },
      {
        "step": 24,
        "train_loss": 0.06432817876338959,
        "param_loss": 0.06432817876338959,
        "tau0_loss": 0.004979342222213745,
        "cfo_loss": 0.0002318139304406941,
        "delay_loss": 0.04421978071331978,
        "doppler_loss": 0.0012133923592045903,
        "rx_offset_loss": 0.013683844357728958,
        "channel_nmse": 0.29606959223747253,
        "channel_nmse_db": -5.2860619443836345,
        "observed_symbol_nmse": 1.7787697004223446e-07,
        "observed_symbol_nmse_db": -67.49877835398539,
        "val_channel_nmse": 0.29606959223747253,
        "val_channel_nmse_db": -5.2860619443836345,
        "val_observed_symbol_nmse": 1.7787697004223446e-07,
        "val_observed_symbol_nmse_db": -67.49877835398539
      }
    ],
    "final": {
      "step": 24,
      "train_loss": 0.06432817876338959,
      "param_loss": 0.06432817876338959,
      "tau0_loss": 0.004979342222213745,
      "cfo_loss": 0.0002318139304406941,
      "delay_loss": 0.04421978071331978,
      "doppler_loss": 0.0012133923592045903,
      "rx_offset_loss": 0.013683844357728958,
      "channel_nmse": 0.29606959223747253,
      "channel_nmse_db": -5.2860619443836345,
      "observed_symbol_nmse": 1.7787697004223446e-07,
      "observed_symbol_nmse_db": -67.49877835398539,
      "val_channel_nmse": 0.29606959223747253,
      "val_channel_nmse_db": -5.2860619443836345,
      "val_observed_symbol_nmse": 1.7787697004223446e-07,
      "val_observed_symbol_nmse_db": -67.49877835398539
    }
  },
  {
    "experiment": "e6_physics_guided_attention",
    "method": "epgt_v1",
    "variant": "bias_scale_0p5",
    "ablation_param": "bias_scale",
    "ablation_value": 0.5,
    "config": {
      "data_config": "configs/data/e1_clean_transformer.yaml",
      "model_config": "configs\\model\\pgt\\epgt_v1_bias_only.yaml",
      "architecture": "epgt_v1",
      "model": {
        "d_model": 32,
        "nhead": 4,
        "num_layers": 1,
        "dim_feedforward": 64,
        "dropout": 0.0,
        "max_rel_delay_s": 3e-06,
        "max_doppler_hz": 200.0,
        "max_total_delay_s": 1e-06,
        "max_cfo_hz": 500.0,
        "max_rx_time_offset_s": 2e-07
      },
      "physics": {
        "use_cross_attention_bias": true,
        "use_reliability_mask": false,
        "center_residual_doppler": true,
        "bias_scale": 0.5,
        "bias_eps": 1e-06,
        "symbol_period_s": 0.001,
        "subcarrier_spacing_hz": 15000.0
      },
      "l_eff": 12
    },
    "history": [
      {
        "step": 0,
        "train_loss": 0.523269772529602,
        "param_loss": 0.523269772529602,
        "tau0_loss": 0.2256353497505188,
        "cfo_loss": 0.027631353586912155,
        "delay_loss": 0.17947183549404144,
        "doppler_loss": 0.040833670645952225,
        "rx_offset_loss": 0.049697574228048325,
        "channel_nmse": 21268906.0,
        "channel_nmse_db": 73.27745151849969,
        "observed_symbol_nmse": 0.026191284880042076,
        "observed_symbol_nmse_db": -15.818431956160516,
        "val_channel_nmse": 21268906.0,
        "val_channel_nmse_db": 73.27745151849969,
        "val_observed_symbol_nmse": 0.026191284880042076,
        "val_observed_symbol_nmse_db": -15.818431956160516
      },
      {
        "step": 1,
        "train_loss": 0.4321310520172119,
        "param_loss": 0.4321310520172119,
        "tau0_loss": 0.16887164115905762,
        "cfo_loss": 0.00146993447560817,
        "delay_loss": 0.17627517879009247,
        "doppler_loss": 0.02959172986447811,
        "rx_offset_loss": 0.055922575294971466
      },
      {
        "step": 2,
        "train_loss": 0.3924183249473572,
        "param_loss": 0.3924183249473572,
        "tau0_loss": 0.17080289125442505,
        "cfo_loss": 0.001917112385854125,
        "delay_loss": 0.170540913939476,
        "doppler_loss": 0.01824248395860195,
        "rx_offset_loss": 0.030914926901459694
      },
      {
        "step": 3,
        "train_loss": 0.3343614935874939,
        "param_loss": 0.3343614935874939,
        "tau0_loss": 0.11884608119726181,
        "cfo_loss": 0.003978578373789787,
        "delay_loss": 0.16755269467830658,
        "doppler_loss": 0.013166612945497036,
        "rx_offset_loss": 0.03081752359867096
      },
      {
        "step": 4,
        "train_loss": 0.31220704317092896,
        "param_loss": 0.31220704317092896,
        "tau0_loss": 0.11983481049537659,
        "cfo_loss": 0.0028877542354166508,
        "delay_loss": 0.16217778623104095,
        "doppler_loss": 0.009515385143458843,
        "rx_offset_loss": 0.01779128797352314,
        "channel_nmse": 894027.25,
        "channel_nmse_db": 59.51350756317474,
        "observed_symbol_nmse": 0.01720055192708969,
        "observed_symbol_nmse_db": -17.644576173088463,
        "val_channel_nmse": 894027.25,
        "val_channel_nmse_db": 59.51350756317474,
        "val_observed_symbol_nmse": 0.01720055192708969,
        "val_observed_symbol_nmse_db": -17.644576173088463
      },
      {
        "step": 5,
        "train_loss": 0.266510933637619,
        "param_loss": 0.266510933637619,
        "tau0_loss": 0.07876253128051758,
        "cfo_loss": 0.0013930248096585274,
        "delay_loss": 0.1595127135515213,
        "doppler_loss": 0.007348600775003433,
        "rx_offset_loss": 0.01949406787753105
      },
      {
        "step": 6,
        "train_loss": 0.2606511414051056,
        "param_loss": 0.2606511414051056,
        "tau0_loss": 0.08176437020301819,
        "cfo_loss": 0.00048637899453751743,
        "delay_loss": 0.15450750291347504,
        "doppler_loss": 0.0068856775760650635,
        "rx_offset_loss": 0.01700720377266407
      },
      {
        "step": 7,
        "train_loss": 0.22834813594818115,
        "param_loss": 0.22834813594818115,
        "tau0_loss": 0.0506439283490181,
        "cfo_loss": 0.0006482586031779647,
        "delay_loss": 0.1516859084367752,
        "doppler_loss": 0.005723683163523674,
        "rx_offset_loss": 0.01964634098112583
      },
      {
        "step": 8,
        "train_loss": 0.22959297895431519,
        "param_loss": 0.22959297895431519,
        "tau0_loss": 0.055755436420440674,
        "cfo_loss": 0.0023903846740722656,
        "delay_loss": 0.14649192988872528,
        "doppler_loss": 0.00646779453381896,
        "rx_offset_loss": 0.018487444147467613
      },
      {
        "step": 9,
        "train_loss": 0.20567330718040466,
        "param_loss": 0.20567330718040466,
        "tau0_loss": 0.032910797744989395,
        "cfo_loss": 0.002239067805930972,
        "delay_loss": 0.14299850165843964,
        "doppler_loss": 0.005342372227460146,
        "rx_offset_loss": 0.02218257449567318,
        "channel_nmse": 97158.15625,
        "channel_nmse_db": 49.87479264695787,
        "observed_symbol_nmse": 0.0044909450225532055,
        "observed_symbol_nmse_db": -23.476622613731827,
        "val_channel_nmse": 97158.15625,
        "val_channel_nmse_db": 49.87479264695787,
        "val_observed_symbol_nmse": 0.0044909450225532055,
        "val_observed_symbol_nmse_db": -23.476622613731827
      },
      {
        "step": 10,
        "train_loss": 0.20308995246887207,
        "param_loss": 0.20308995246887207,
        "tau0_loss": 0.03951316326856613,
        "cfo_loss": 0.0021945228800177574,
        "delay_loss": 0.1370963454246521,
        "doppler_loss": 0.005640869960188866,
        "rx_offset_loss": 0.01864505559206009
      },
      {
        "step": 11,
        "train_loss": 0.1818799376487732,
        "param_loss": 0.1818799376487732,
        "tau0_loss": 0.022429855540394783,
        "cfo_loss": 0.000711078115273267,
        "delay_loss": 0.1325220912694931,
        "doppler_loss": 0.004212655127048492,
        "rx_offset_loss": 0.02200424298644066
      },
      {
        "step": 12,
        "train_loss": 0.17595429718494415,
        "param_loss": 0.17595429718494415,
        "tau0_loss": 0.029339350759983063,
        "cfo_loss": 0.00029405386885628104,
        "delay_loss": 0.12577174603939056,
        "doppler_loss": 0.0037843461614102125,
        "rx_offset_loss": 0.0167648084461689
      },
      {
        "step": 13,
        "train_loss": 0.15789367258548737,
        "param_loss": 0.15789367258548737,
        "tau0_loss": 0.015868451446294785,
        "cfo_loss": 0.00043242331594228745,
        "delay_loss": 0.1201927587389946,
        "doppler_loss": 0.0026995399966835976,
        "rx_offset_loss": 0.0187004916369915
      },
      {
        "step": 14,
        "train_loss": 0.15231123566627502,
        "param_loss": 0.15231123566627502,
        "tau0_loss": 0.022341527044773102,
        "cfo_loss": 0.000710188876837492,
        "delay_loss": 0.11283567547798157,
        "doppler_loss": 0.0020827744156122208,
        "rx_offset_loss": 0.014341074973344803,
        "channel_nmse": 3201.78515625,
        "channel_nmse_db": 35.05392186863268,
        "observed_symbol_nmse": 0.0006324193091131747,
        "observed_symbol_nmse_db": -31.989948779119295,
        "val_channel_nmse": 3201.78515625,
        "val_channel_nmse_db": 35.05392186863268,
        "val_observed_symbol_nmse": 0.0006324193091131747,
        "val_observed_symbol_nmse_db": -31.989948779119295
      },
      {
        "step": 15,
        "train_loss": 0.1368783861398697,
        "param_loss": 0.1368783861398697,
        "tau0_loss": 0.01138403918594122,
        "cfo_loss": 0.0010663499124348164,
        "delay_loss": 0.10662991553544998,
        "doppler_loss": 0.0018291632877662778,
        "rx_offset_loss": 0.015968922525644302
      },
      {
        "step": 16,
        "train_loss": 0.1321505457162857,
        "param_loss": 0.1321505457162857,
        "tau0_loss": 0.017182867974042892,
        "cfo_loss": 0.0005260144826024771,
        "delay_loss": 0.09906395524740219,
        "doppler_loss": 0.001433852594345808,
        "rx_offset_loss": 0.013943860307335854
      },
      {
        "step": 17,
        "train_loss": 0.11914733052253723,
        "param_loss": 0.11914733052253723,
        "tau0_loss": 0.008253108710050583,
        "cfo_loss": 0.00029500576783902943,
        "delay_loss": 0.09260528534650803,
        "doppler_loss": 0.001920494600199163,
        "rx_offset_loss": 0.01607343554496765
      },
      {
        "step": 18,
        "train_loss": 0.11514110118150711,
        "param_loss": 0.11514110118150711,
        "tau0_loss": 0.013411106541752815,
        "cfo_loss": 0.00012902541493531317,
        "delay_loss": 0.08518306165933609,
        "doppler_loss": 0.0017402530647814274,
        "rx_offset_loss": 0.014677651226520538
      },
      {
        "step": 19,
        "train_loss": 0.10433901846408844,
        "param_loss": 0.10433901846408844,
        "tau0_loss": 0.006185287609696388,
        "cfo_loss": 0.000230558289331384,
        "delay_loss": 0.07868272066116333,
        "doppler_loss": 0.0024437769316136837,
        "rx_offset_loss": 0.01679667830467224,
        "channel_nmse": 68.32071685791016,
        "channel_nmse_db": 18.345524145574387,
        "observed_symbol_nmse": 2.773470441752579e-05,
        "observed_symbol_nmse_db": -45.569764425928774,
        "val_channel_nmse": 68.32071685791016,
        "val_channel_nmse_db": 18.345524145574387,
        "val_observed_symbol_nmse": 2.773470441752579e-05,
        "val_observed_symbol_nmse_db": -45.569764425928774
      },
      {
        "step": 20,
        "train_loss": 0.09910742193460464,
        "param_loss": 0.09910742193460464,
        "tau0_loss": 0.010829184204339981,
        "cfo_loss": 0.0004432955465745181,
        "delay_loss": 0.0715898796916008,
        "doppler_loss": 0.0021963671315461397,
        "rx_offset_loss": 0.014048694632947445
      },
      {
        "step": 21,
        "train_loss": 0.08943437039852142,
        "param_loss": 0.08943437039852142,
        "tau0_loss": 0.004922259598970413,
        "cfo_loss": 0.00025069035473279655,
        "delay_loss": 0.06523970514535904,
        "doppler_loss": 0.0025552972219884396,
        "rx_offset_loss": 0.0164664164185524
      },
      {
        "step": 22,
        "train_loss": 0.08284004032611847,
        "param_loss": 0.08284004032611847,
        "tau0_loss": 0.009152917191386223,
        "cfo_loss": 0.00015542461187578738,
        "delay_loss": 0.058689218014478683,
        "doppler_loss": 0.001980516593903303,
        "rx_offset_loss": 0.012861964292824268
      },
      {
        "step": 23,
        "train_loss": 0.07495708763599396,
        "param_loss": 0.07495708763599396,
        "tau0_loss": 0.004158942028880119,
        "cfo_loss": 0.00013464843505062163,
        "delay_loss": 0.05274158716201782,
        "doppler_loss": 0.0018632756546139717,
        "rx_offset_loss": 0.016058631241321564
      },
      {
        "step": 24,
        "train_loss": 0.06887499988079071,
        "param_loss": 0.06887499988079071,
        "tau0_loss": 0.00803336314857006,
        "cfo_loss": 0.00015774075291119516,
        "delay_loss": 0.04691322147846222,
        "doppler_loss": 0.001192693249322474,
        "rx_offset_loss": 0.012577978894114494,
        "channel_nmse": 1.8403218984603882,
        "channel_nmse_db": 2.6489379393258483,
        "observed_symbol_nmse": 2.0070799564564368e-06,
        "observed_symbol_nmse_db": -56.9743510970822,
        "val_channel_nmse": 1.8403218984603882,
        "val_channel_nmse_db": 2.6489379393258483,
        "val_observed_symbol_nmse": 2.0070799564564368e-06,
        "val_observed_symbol_nmse_db": -56.9743510970822
      }
    ],
    "final": {
      "step": 24,
      "train_loss": 0.06887499988079071,
      "param_loss": 0.06887499988079071,
      "tau0_loss": 0.00803336314857006,
      "cfo_loss": 0.00015774075291119516,
      "delay_loss": 0.04691322147846222,
      "doppler_loss": 0.001192693249322474,
      "rx_offset_loss": 0.012577978894114494,
      "channel_nmse": 1.8403218984603882,
      "channel_nmse_db": 2.6489379393258483,
      "observed_symbol_nmse": 2.0070799564564368e-06,
      "observed_symbol_nmse_db": -56.9743510970822,
      "val_channel_nmse": 1.8403218984603882,
      "val_channel_nmse_db": 2.6489379393258483,
      "val_observed_symbol_nmse": 2.0070799564564368e-06,
      "val_observed_symbol_nmse_db": -56.9743510970822
    }
  },
  {
    "experiment": "e6_physics_guided_attention",
    "method": "epgt_v1",
    "variant": "bias_scale_1p0",
    "ablation_param": "bias_scale",
    "ablation_value": 1.0,
    "config": {
      "data_config": "configs/data/e1_clean_transformer.yaml",
      "model_config": "configs\\model\\pgt\\epgt_v1_bias_only.yaml",
      "architecture": "epgt_v1",
      "model": {
        "d_model": 32,
        "nhead": 4,
        "num_layers": 1,
        "dim_feedforward": 64,
        "dropout": 0.0,
        "max_rel_delay_s": 3e-06,
        "max_doppler_hz": 200.0,
        "max_total_delay_s": 1e-06,
        "max_cfo_hz": 500.0,
        "max_rx_time_offset_s": 2e-07
      },
      "physics": {
        "use_cross_attention_bias": true,
        "use_reliability_mask": false,
        "center_residual_doppler": true,
        "bias_scale": 1.0,
        "bias_eps": 1e-06,
        "symbol_period_s": 0.001,
        "subcarrier_spacing_hz": 15000.0
      },
      "l_eff": 12
    },
    "history": [
      {
        "step": 0,
        "train_loss": 0.419096440076828,
        "param_loss": 0.419096440076828,
        "tau0_loss": 0.1535699963569641,
        "cfo_loss": 0.004209285601973534,
        "delay_loss": 0.18805408477783203,
        "doppler_loss": 0.01814443990588188,
        "rx_offset_loss": 0.05511864274740219,
        "channel_nmse": 302815.125,
        "channel_nmse_db": 54.81177563496428,
        "observed_symbol_nmse": 0.011944358237087727,
        "observed_symbol_nmse_db": -19.228371796223165,
        "val_channel_nmse": 302815.125,
        "val_channel_nmse_db": 54.81177563496428,
        "val_observed_symbol_nmse": 0.011944358237087727,
        "val_observed_symbol_nmse_db": -19.228371796223165
      },
      {
        "step": 1,
        "train_loss": 0.33745044469833374,
        "param_loss": 0.33745044469833374,
        "tau0_loss": 0.09826979786157608,
        "cfo_loss": 0.003194911405444145,
        "delay_loss": 0.18292216956615448,
        "doppler_loss": 0.011322841979563236,
        "rx_offset_loss": 0.04174070432782173
      },
      {
        "step": 2,
        "train_loss": 0.30890026688575745,
        "param_loss": 0.30890026688575745,
        "tau0_loss": 0.10193478316068649,
        "cfo_loss": 0.002632430987432599,
        "delay_loss": 0.17472724616527557,
        "doppler_loss": 0.006604677531868219,
        "rx_offset_loss": 0.023001141846179962
      },
      {
        "step": 3,
        "train_loss": 0.2625487148761749,
        "param_loss": 0.2625487148761749,
        "tau0_loss": 0.060822248458862305,
        "cfo_loss": 0.002194845350459218,
        "delay_loss": 0.16941390931606293,
        "doppler_loss": 0.0054700965993106365,
        "rx_offset_loss": 0.024647623300552368
      },
      {
        "step": 4,
        "train_loss": 0.251986026763916,
        "param_loss": 0.251986026763916,
        "tau0_loss": 0.0663473978638649,
        "cfo_loss": 0.0013873393181711435,
        "delay_loss": 0.16210047900676727,
        "doppler_loss": 0.006317036226391792,
        "rx_offset_loss": 0.015833795070648193,
        "channel_nmse": 59863.03125,
        "channel_nmse_db": 47.7715870418171,
        "observed_symbol_nmse": 0.0021617203019559383,
        "observed_symbol_nmse_db": -26.652004985144554,
        "val_channel_nmse": 59863.03125,
        "val_channel_nmse_db": 47.7715870418171,
        "val_observed_symbol_nmse": 0.0021617203019559383,
        "val_observed_symbol_nmse_db": -26.652004985144554
      },
      {
        "step": 5,
        "train_loss": 0.2234976887702942,
        "param_loss": 0.2234976887702942,
        "tau0_loss": 0.036983124911785126,
        "cfo_loss": 0.0013981256633996964,
        "delay_loss": 0.1575143188238144,
        "doppler_loss": 0.005319752264767885,
        "rx_offset_loss": 0.02228236012160778
      },
      {
        "step": 6,
        "train_loss": 0.21593868732452393,
        "param_loss": 0.21593868732452393,
        "tau0_loss": 0.04337957873940468,
        "cfo_loss": 0.0006017911946401,
        "delay_loss": 0.15056374669075012,
        "doppler_loss": 0.0056672184728085995,
        "rx_offset_loss": 0.01572633534669876
      },
      {
        "step": 7,
        "train_loss": 0.19590184092521667,
        "param_loss": 0.19590184092521667,
        "tau0_loss": 0.022505618631839752,
        "cfo_loss": 0.0013432401465252042,
        "delay_loss": 0.14614064991474152,
        "doppler_loss": 0.0042116218246519566,
        "rx_offset_loss": 0.021700715646147728
      },
      {
        "step": 8,
        "train_loss": 0.18804794549942017,
        "param_loss": 0.18804794549942017,
        "tau0_loss": 0.028685187920928,
        "cfo_loss": 0.00035489158472046256,
        "delay_loss": 0.1390850841999054,
        "doppler_loss": 0.004144926089793444,
        "rx_offset_loss": 0.015777863562107086
      },
      {
        "step": 9,
        "train_loss": 0.17253942787647247,
        "param_loss": 0.17253942787647247,
        "tau0_loss": 0.01377863623201847,
        "cfo_loss": 0.0009561952319927514,
        "delay_loss": 0.13449619710445404,
        "doppler_loss": 0.003351423656567931,
        "rx_offset_loss": 0.019956978037953377,
        "channel_nmse": 322.9069519042969,
        "channel_nmse_db": 25.09077395098224,
        "observed_symbol_nmse": 0.00020062358817085624,
        "observed_symbol_nmse_db": -36.97618004294499,
        "val_channel_nmse": 322.9069519042969,
        "val_channel_nmse_db": 25.09077395098224,
        "val_observed_symbol_nmse": 0.00020062358817085624,
        "val_observed_symbol_nmse_db": -36.97618004294499
      },
      {
        "step": 10,
        "train_loss": 0.16504879295825958,
        "param_loss": 0.16504879295825958,
        "tau0_loss": 0.019261986017227173,
        "cfo_loss": 0.00033254639129154384,
        "delay_loss": 0.12733465433120728,
        "doppler_loss": 0.003177767852321267,
        "rx_offset_loss": 0.014941845089197159
      },
      {
        "step": 11,
        "train_loss": 0.15311689674854279,
        "param_loss": 0.15311689674854279,
        "tau0_loss": 0.008553632535040379,
        "cfo_loss": 0.0008527369354851544,
        "delay_loss": 0.12247288227081299,
        "doppler_loss": 0.002757183276116848,
        "rx_offset_loss": 0.018480461090803146
      },
      {
        "step": 12,
        "train_loss": 0.1455826610326767,
        "param_loss": 0.1455826610326767,
        "tau0_loss": 0.01326123345643282,
        "cfo_loss": 0.00016077738837338984,
        "delay_loss": 0.11517339199781418,
        "doppler_loss": 0.0023816791363060474,
        "rx_offset_loss": 0.01460557896643877
      },
      {
        "step": 13,
        "train_loss": 0.13675038516521454,
        "param_loss": 0.13675038516521454,
        "tau0_loss": 0.0055753993801772594,
        "cfo_loss": 0.0006836555548943579,
        "delay_loss": 0.10994479060173035,
        "doppler_loss": 0.0019097384065389633,
        "rx_offset_loss": 0.018636804074048996
      },
      {
        "step": 14,
        "train_loss": 0.12898163497447968,
        "param_loss": 0.12898163497447968,
        "tau0_loss": 0.009570760652422905,
        "cfo_loss": 0.00021491262305062264,
        "delay_loss": 0.10252707451581955,
        "doppler_loss": 0.0015566893853247166,
        "rx_offset_loss": 0.015112199820578098,
        "channel_nmse": 12.196537971496582,
        "channel_nmse_db": 10.86236572211876,
        "observed_symbol_nmse": 2.2000653189024888e-05,
        "observed_symbol_nmse_db": -46.575644052478125,
        "val_channel_nmse": 12.196537971496582,
        "val_channel_nmse_db": 10.86236572211876,
        "val_observed_symbol_nmse": 2.2000653189024888e-05,
        "val_observed_symbol_nmse_db": -46.575644052478125
      },
      {
        "step": 15,
        "train_loss": 0.12174665927886963,
        "param_loss": 0.12174665927886963,
        "tau0_loss": 0.003996662795543671,
        "cfo_loss": 0.0005564374732784927,
        "delay_loss": 0.09700874239206314,
        "doppler_loss": 0.0012493716785684228,
        "rx_offset_loss": 0.018935441970825195
      },
      {
        "step": 16,
        "train_loss": 0.11337126046419144,
        "param_loss": 0.11337126046419144,
        "tau0_loss": 0.007384723983705044,
        "cfo_loss": 8.829499711282551e-05,
        "delay_loss": 0.08971301466226578,
        "doppler_loss": 0.0011782528599724174,
        "rx_offset_loss": 0.015006976202130318
      },
      {
        "step": 17,
        "train_loss": 0.10707428306341171,
        "param_loss": 0.10707428306341171,
        "tau0_loss": 0.003201055806130171,
        "cfo_loss": 0.00044816621812060475,
        "delay_loss": 0.08414974063634872,
        "doppler_loss": 0.0010714642703533173,
        "rx_offset_loss": 0.0182038601487875
      },
      {
        "step": 18,
        "train_loss": 0.09859316051006317,
        "param_loss": 0.09859316051006317,
        "tau0_loss": 0.0060925837606191635,
        "cfo_loss": 7.811299292370677e-05,
        "delay_loss": 0.07721942663192749,
        "doppler_loss": 0.0010468697873875499,
        "rx_offset_loss": 0.014156167395412922
      },
      {
        "step": 19,
        "train_loss": 0.09342440962791443,
        "param_loss": 0.09342440962791443,
        "tau0_loss": 0.002801105845719576,
        "cfo_loss": 0.00033271845313720405,
        "delay_loss": 0.07183461636304855,
        "doppler_loss": 0.000938517099712044,
        "rx_offset_loss": 0.01751745119690895,
        "channel_nmse": 0.5115111470222473,
        "channel_nmse_db": -2.911448975570288,
        "observed_symbol_nmse": 1.3905884088671883e-06,
        "observed_symbol_nmse_db": -58.56801082650715,
        "val_channel_nmse": 0.5115111470222473,
        "val_channel_nmse_db": -2.911448975570288,
        "val_observed_symbol_nmse": 1.3905884088671883e-06,
        "val_observed_symbol_nmse_db": -58.56801082650715
      },
      {
        "step": 20,
        "train_loss": 0.08547084778547287,
        "param_loss": 0.08547084778547287,
        "tau0_loss": 0.0053054774180054665,
        "cfo_loss": 0.000112907488073688,
        "delay_loss": 0.0654439851641655,
        "doppler_loss": 0.000906486704479903,
        "rx_offset_loss": 0.01370199304074049
      },
      {
        "step": 21,
        "train_loss": 0.08174090087413788,
        "param_loss": 0.08174090087413788,
        "tau0_loss": 0.0025886548683047295,
        "cfo_loss": 0.0002867738367058337,
        "delay_loss": 0.06041884422302246,
        "doppler_loss": 0.000910030968952924,
        "rx_offset_loss": 0.017536597326397896
      },
      {
        "step": 22,
        "train_loss": 0.07426512986421585,
        "param_loss": 0.07426512986421585,
        "tau0_loss": 0.004772252403199673,
        "cfo_loss": 8.077365782810375e-05,
        "delay_loss": 0.05466427281498909,
        "doppler_loss": 0.0009473187965340912,
        "rx_offset_loss": 0.013800512999296188
      },
      {
        "step": 23,
        "train_loss": 0.071256622672081,
        "param_loss": 0.071256622672081,
        "tau0_loss": 0.0024643370416015387,
        "cfo_loss": 0.00025119358906522393,
        "delay_loss": 0.05007855221629143,
        "doppler_loss": 0.00090752326650545,
        "rx_offset_loss": 0.017555013298988342
      },
      {
        "step": 24,
        "train_loss": 0.0639166608452797,
        "param_loss": 0.0639166608452797,
        "tau0_loss": 0.004351656883955002,
        "cfo_loss": 9.723663970362395e-05,
        "delay_loss": 0.04499411955475807,
        "doppler_loss": 0.0007690955535508692,
        "rx_offset_loss": 0.013704548589885235,
        "channel_nmse": 0.022315792739391327,
        "channel_nmse_db": -16.513876807857034,
        "observed_symbol_nmse": 8.992961397780164e-08,
        "observed_symbol_nmse_db": -70.46092441544162,
        "val_channel_nmse": 0.022315792739391327,
        "val_channel_nmse_db": -16.513876807857034,
        "val_observed_symbol_nmse": 8.992961397780164e-08,
        "val_observed_symbol_nmse_db": -70.46092441544162
      }
    ],
    "final": {
      "step": 24,
      "train_loss": 0.0639166608452797,
      "param_loss": 0.0639166608452797,
      "tau0_loss": 0.004351656883955002,
      "cfo_loss": 9.723663970362395e-05,
      "delay_loss": 0.04499411955475807,
      "doppler_loss": 0.0007690955535508692,
      "rx_offset_loss": 0.013704548589885235,
      "channel_nmse": 0.022315792739391327,
      "channel_nmse_db": -16.513876807857034,
      "observed_symbol_nmse": 8.992961397780164e-08,
      "observed_symbol_nmse_db": -70.46092441544162,
      "val_channel_nmse": 0.022315792739391327,
      "val_channel_nmse_db": -16.513876807857034,
      "val_observed_symbol_nmse": 8.992961397780164e-08,
      "val_observed_symbol_nmse_db": -70.46092441544162
    }
  },
  {
    "experiment": "e6_physics_guided_attention",
    "method": "epgt_v1",
    "variant": "bias_scale_2p0",
    "ablation_param": "bias_scale",
    "ablation_value": 2.0,
    "config": {
      "data_config": "configs/data/e1_clean_transformer.yaml",
      "model_config": "configs\\model\\pgt\\epgt_v1_bias_only.yaml",
      "architecture": "epgt_v1",
      "model": {
        "d_model": 32,
        "nhead": 4,
        "num_layers": 1,
        "dim_feedforward": 64,
        "dropout": 0.0,
        "max_rel_delay_s": 3e-06,
        "max_doppler_hz": 200.0,
        "max_total_delay_s": 1e-06,
        "max_cfo_hz": 500.0,
        "max_rx_time_offset_s": 2e-07
      },
      "physics": {
        "use_cross_attention_bias": true,
        "use_reliability_mask": false,
        "center_residual_doppler": true,
        "bias_scale": 2.0,
        "bias_eps": 1e-06,
        "symbol_period_s": 0.001,
        "subcarrier_spacing_hz": 15000.0
      },
      "l_eff": 12
    },
    "history": [
      {
        "step": 0,
        "train_loss": 0.5030075907707214,
        "param_loss": 0.5030075907707214,
        "tau0_loss": 0.19440291821956635,
        "cfo_loss": 0.039354871958494186,
        "delay_loss": 0.20034612715244293,
        "doppler_loss": 0.0250585675239563,
        "rx_offset_loss": 0.04384513199329376,
        "channel_nmse": 3572696.75,
        "channel_nmse_db": 65.52996154911982,
        "observed_symbol_nmse": 0.01813296042382717,
        "observed_symbol_nmse_db": -17.415312862956604,
        "val_channel_nmse": 3572696.75,
        "val_channel_nmse_db": 65.52996154911982,
        "val_observed_symbol_nmse": 0.01813296042382717,
        "val_observed_symbol_nmse_db": -17.415312862956604
      },
      {
        "step": 1,
        "train_loss": 0.3856906592845917,
        "param_loss": 0.3856906592845917,
        "tau0_loss": 0.14440280199050903,
        "cfo_loss": 0.006317997816950083,
        "delay_loss": 0.19490663707256317,
        "doppler_loss": 0.01580669730901718,
        "rx_offset_loss": 0.024256514385342598
      },
      {
        "step": 2,
        "train_loss": 0.36573487520217896,
        "param_loss": 0.36573487520217896,
        "tau0_loss": 0.1393946260213852,
        "cfo_loss": 0.006064145360141993,
        "delay_loss": 0.18940193951129913,
        "doppler_loss": 0.008862928487360477,
        "rx_offset_loss": 0.022011209279298782
      },
      {
        "step": 3,
        "train_loss": 0.31163421273231506,
        "param_loss": 0.31163421273231506,
        "tau0_loss": 0.091990165412426,
        "cfo_loss": 0.009706688113510609,
        "delay_loss": 0.18445944786071777,
        "doppler_loss": 0.007136309519410133,
        "rx_offset_loss": 0.018341589719057083
      },
      {
        "step": 4,
        "train_loss": 0.29783737659454346,
        "param_loss": 0.29783737659454346,
        "tau0_loss": 0.09042820334434509,
        "cfo_loss": 0.0034671593457460403,
        "delay_loss": 0.17926587164402008,
        "doppler_loss": 0.007413599174469709,
        "rx_offset_loss": 0.017262551933526993,
        "channel_nmse": 49315.87890625,
        "channel_nmse_db": 46.92986777513026,
        "observed_symbol_nmse": 0.003376908367499709,
        "observed_symbol_nmse_db": -24.71480723668661,
        "val_channel_nmse": 49315.87890625,
        "val_channel_nmse_db": 46.92986777513026,
        "val_observed_symbol_nmse": 0.003376908367499709,
        "val_observed_symbol_nmse_db": -24.71480723668661
      },
      {
        "step": 5,
        "train_loss": 0.2585590183734894,
        "param_loss": 0.2585590183734894,
        "tau0_loss": 0.05587373673915863,
        "cfo_loss": 0.0029422733932733536,
        "delay_loss": 0.17430035769939423,
        "doppler_loss": 0.007612061221152544,
        "rx_offset_loss": 0.017830608412623405
      },
      {
        "step": 6,
        "train_loss": 0.2591746747493744,
        "param_loss": 0.2591746747493744,
        "tau0_loss": 0.05976444482803345,
        "cfo_loss": 0.003202358027920127,
        "delay_loss": 0.1693950891494751,
        "doppler_loss": 0.008575193583965302,
        "rx_offset_loss": 0.01823759637773037
      },
      {
        "step": 7,
        "train_loss": 0.2280885875225067,
        "param_loss": 0.2280885875225067,
        "tau0_loss": 0.03493750840425491,
        "cfo_loss": 0.003829660825431347,
        "delay_loss": 0.16406182944774628,
        "doppler_loss": 0.007220080122351646,
        "rx_offset_loss": 0.018039502203464508
      },
      {
        "step": 8,
        "train_loss": 0.22928696870803833,
        "param_loss": 0.22928696870803833,
        "tau0_loss": 0.04160216450691223,
        "cfo_loss": 0.0023579841945320368,
        "delay_loss": 0.15898914635181427,
        "doppler_loss": 0.006730413064360619,
        "rx_offset_loss": 0.01960725337266922
      },
      {
        "step": 9,
        "train_loss": 0.1996026337146759,
        "param_loss": 0.1996026337146759,
        "tau0_loss": 0.023009952157735825,
        "cfo_loss": 0.001265944680199027,
        "delay_loss": 0.15318718552589417,
        "doppler_loss": 0.004784640856087208,
        "rx_offset_loss": 0.01735491305589676,
        "channel_nmse": 5487.27685546875,
        "channel_nmse_db": 37.393568726745,
        "observed_symbol_nmse": 0.0009841988794505596,
        "observed_symbol_nmse_db": -30.069171333218737,
        "val_channel_nmse": 5487.27685546875,
        "val_channel_nmse_db": 37.393568726745,
        "val_observed_symbol_nmse": 0.0009841988794505596,
        "val_observed_symbol_nmse_db": -30.069171333218737
      },
      {
        "step": 10,
        "train_loss": 0.20263169705867767,
        "param_loss": 0.20263169705867767,
        "tau0_loss": 0.030315155163407326,
        "cfo_loss": 0.0018124235793948174,
        "delay_loss": 0.1477617770433426,
        "doppler_loss": 0.004024226684123278,
        "rx_offset_loss": 0.018718119710683823
      },
      {
        "step": 11,
        "train_loss": 0.17897526919841766,
        "param_loss": 0.17897526919841766,
        "tau0_loss": 0.015897683799266815,
        "cfo_loss": 0.0028167669661343098,
        "delay_loss": 0.14141662418842316,
        "doppler_loss": 0.0028641673270612955,
        "rx_offset_loss": 0.015980036929249763
      },
      {
        "step": 12,
        "train_loss": 0.18051356077194214,
        "param_loss": 0.18051356077194214,
        "tau0_loss": 0.022985607385635376,
        "cfo_loss": 0.0026000901125371456,
        "delay_loss": 0.13560813665390015,
        "doppler_loss": 0.0024627838283777237,
        "rx_offset_loss": 0.016856933012604713
      },
      {
        "step": 13,
        "train_loss": 0.15951105952262878,
        "param_loss": 0.15951105952262878,
        "tau0_loss": 0.011492511257529259,
        "cfo_loss": 0.001318138325586915,
        "delay_loss": 0.1288752406835556,
        "doppler_loss": 0.0020076001528650522,
        "rx_offset_loss": 0.015817567706108093
      },
      {
        "step": 14,
        "train_loss": 0.15948531031608582,
        "param_loss": 0.15948531031608582,
        "tau0_loss": 0.017988605424761772,
        "cfo_loss": 0.0008220444433391094,
        "delay_loss": 0.12276792526245117,
        "doppler_loss": 0.001868465798906982,
        "rx_offset_loss": 0.016038276255130768,
        "channel_nmse": 640.0741577148438,
        "channel_nmse_db": 28.062302933910708,
        "observed_symbol_nmse": 0.00021388294408097863,
        "observed_symbol_nmse_db": -36.698238444725206,
        "val_channel_nmse": 640.0741577148438,
        "val_channel_nmse_db": 28.062302933910708,
        "val_observed_symbol_nmse": 0.00021388294408097863,
        "val_observed_symbol_nmse_db": -36.698238444725206
      },
      {
        "step": 15,
        "train_loss": 0.14376448094844818,
        "param_loss": 0.14376448094844818,
        "tau0_loss": 0.008616246283054352,
        "cfo_loss": 0.0008298000902868807,
        "delay_loss": 0.11576773971319199,
        "doppler_loss": 0.001798612647689879,
        "rx_offset_loss": 0.016752080991864204
      },
      {
        "step": 16,
        "train_loss": 0.14300107955932617,
        "param_loss": 0.14300107955932617,
        "tau0_loss": 0.014451783150434494,
        "cfo_loss": 0.0016530980356037617,
        "delay_loss": 0.1093650832772255,
        "doppler_loss": 0.0018400093540549278,
        "rx_offset_loss": 0.01569109410047531
      },
      {
        "step": 17,
        "train_loss": 0.12897148728370667,
        "param_loss": 0.12897148728370667,
        "tau0_loss": 0.006714169401675463,
        "cfo_loss": 0.0011792004806920886,
        "delay_loss": 0.10216585546731949,
        "doppler_loss": 0.0019649704918265343,
        "rx_offset_loss": 0.016947295516729355
      },
      {
        "step": 18,
        "train_loss": 0.12555165588855743,
        "param_loss": 0.12555165588855743,
        "tau0_loss": 0.011943037621676922,
        "cfo_loss": 0.0009070050437003374,
        "delay_loss": 0.09561753273010254,
        "doppler_loss": 0.002049187198281288,
        "rx_offset_loss": 0.01503489539027214
      },
      {
        "step": 19,
        "train_loss": 0.11240626126527786,
        "param_loss": 0.11240626126527786,
        "tau0_loss": 0.0054345945827662945,
        "cfo_loss": 0.00028805172769352794,
        "delay_loss": 0.08849260210990906,
        "doppler_loss": 0.002110204892233014,
        "rx_offset_loss": 0.01608080230653286,
        "channel_nmse": 317.6876525878906,
        "channel_nmse_db": 25.02000335641903,
        "observed_symbol_nmse": 4.393925701151602e-05,
        "observed_symbol_nmse_db": -43.5714728114844,
        "val_channel_nmse": 317.6876525878906,
        "val_channel_nmse_db": 25.02000335641903,
        "val_observed_symbol_nmse": 4.393925701151602e-05,
        "val_observed_symbol_nmse_db": -43.5714728114844
      },
      {
        "step": 20,
        "train_loss": 0.10949509590864182,
        "param_loss": 0.10949509590864182,
        "tau0_loss": 0.01006256602704525,
        "cfo_loss": 0.0007071350701153278,
        "delay_loss": 0.08205012232065201,
        "doppler_loss": 0.002079577650874853,
        "rx_offset_loss": 0.014595694839954376
      },
      {
        "step": 21,
        "train_loss": 0.09751933068037033,
        "param_loss": 0.09751933068037033,
        "tau0_loss": 0.004504133481532335,
        "cfo_loss": 0.0008266055956482887,
        "delay_loss": 0.07528506964445114,
        "doppler_loss": 0.0018344013951718807,
        "rx_offset_loss": 0.015069122426211834
      },
      {
        "step": 22,
        "train_loss": 0.09518205374479294,
        "param_loss": 0.09518205374479294,
        "tau0_loss": 0.008517229929566383,
        "cfo_loss": 0.0008193299290724099,
        "delay_loss": 0.069168820977211,
        "doppler_loss": 0.0017690970562398434,
        "rx_offset_loss": 0.014907577075064182
      },
      {
        "step": 23,
        "train_loss": 0.08289292454719543,
        "param_loss": 0.08289292454719543,
        "tau0_loss": 0.003799165366217494,
        "cfo_loss": 0.00032147462479770184,
        "delay_loss": 0.06288927048444748,
        "doppler_loss": 0.0013392543187364936,
        "rx_offset_loss": 0.014543754979968071
      },
      {
        "step": 24,
        "train_loss": 0.08171232044696808,
        "param_loss": 0.08171232044696808,
        "tau0_loss": 0.0072379265911877155,
        "cfo_loss": 0.0003649221616797149,
        "delay_loss": 0.057186245918273926,
        "doppler_loss": 0.0015668357955291867,
        "rx_offset_loss": 0.015356389805674553,
        "channel_nmse": 20.556188583374023,
        "channel_nmse_db": 13.12942593268023,
        "observed_symbol_nmse": 4.620528216037201e-06,
        "observed_symbol_nmse_db": -53.353082793265614,
        "val_channel_nmse": 20.556188583374023,
        "val_channel_nmse_db": 13.12942593268023,
        "val_observed_symbol_nmse": 4.620528216037201e-06,
        "val_observed_symbol_nmse_db": -53.353082793265614
      }
    ],
    "final": {
      "step": 24,
      "train_loss": 0.08171232044696808,
      "param_loss": 0.08171232044696808,
      "tau0_loss": 0.0072379265911877155,
      "cfo_loss": 0.0003649221616797149,
      "delay_loss": 0.057186245918273926,
      "doppler_loss": 0.0015668357955291867,
      "rx_offset_loss": 0.015356389805674553,
      "channel_nmse": 20.556188583374023,
      "channel_nmse_db": 13.12942593268023,
      "observed_symbol_nmse": 4.620528216037201e-06,
      "observed_symbol_nmse_db": -53.353082793265614,
      "val_channel_nmse": 20.556188583374023,
      "val_channel_nmse_db": 13.12942593268023,
      "val_observed_symbol_nmse": 4.620528216037201e-06,
      "val_observed_symbol_nmse_db": -53.353082793265614
    }
  },
  {
    "experiment": "e6_physics_guided_attention",
    "method": "epgt_v1",
    "variant": "bias_scale_4p0",
    "ablation_param": "bias_scale",
    "ablation_value": 4.0,
    "config": {
      "data_config": "configs/data/e1_clean_transformer.yaml",
      "model_config": "configs\\model\\pgt\\epgt_v1_bias_only.yaml",
      "architecture": "epgt_v1",
      "model": {
        "d_model": 32,
        "nhead": 4,
        "num_layers": 1,
        "dim_feedforward": 64,
        "dropout": 0.0,
        "max_rel_delay_s": 3e-06,
        "max_doppler_hz": 200.0,
        "max_total_delay_s": 1e-06,
        "max_cfo_hz": 500.0,
        "max_rx_time_offset_s": 2e-07
      },
      "physics": {
        "use_cross_attention_bias": true,
        "use_reliability_mask": false,
        "center_residual_doppler": true,
        "bias_scale": 4.0,
        "bias_eps": 1e-06,
        "symbol_period_s": 0.001,
        "subcarrier_spacing_hz": 15000.0
      },
      "l_eff": 12
    },
    "history": [
      {
        "step": 0,
        "train_loss": 0.5984311699867249,
        "param_loss": 0.5984311699867249,
        "tau0_loss": 0.16167879104614258,
        "cfo_loss": 0.11583136022090912,
        "delay_loss": 0.1971731185913086,
        "doppler_loss": 0.05102155730128288,
        "rx_offset_loss": 0.0727263018488884,
        "channel_nmse": 10674213.0,
        "channel_nmse_db": 70.28335864740914,
        "observed_symbol_nmse": 0.01973516307771206,
        "observed_symbol_nmse_db": -17.04759280522981,
        "val_channel_nmse": 10674213.0,
        "val_channel_nmse_db": 70.28335864740914,
        "val_observed_symbol_nmse": 0.01973516307771206,
        "val_observed_symbol_nmse_db": -17.04759280522981
      },
      {
        "step": 1,
        "train_loss": 0.4257373511791229,
        "param_loss": 0.4257373511791229,
        "tau0_loss": 0.12422161549329758,
        "cfo_loss": 0.030226511880755424,
        "delay_loss": 0.19537444412708282,
        "doppler_loss": 0.030630091205239296,
        "rx_offset_loss": 0.0452846959233284
      },
      {
        "step": 2,
        "train_loss": 0.39021655917167664,
        "param_loss": 0.39021655917167664,
        "tau0_loss": 0.14192233979701996,
        "cfo_loss": 0.001506578759290278,
        "delay_loss": 0.1959977149963379,
        "doppler_loss": 0.01632673293352127,
        "rx_offset_loss": 0.03446319326758385
      },
      {
        "step": 3,
        "train_loss": 0.340461403131485,
        "param_loss": 0.340461403131485,
        "tau0_loss": 0.10282041132450104,
        "cfo_loss": 0.013663613237440586,
        "delay_loss": 0.19362705945968628,
        "doppler_loss": 0.010916240513324738,
        "rx_offset_loss": 0.019434094429016113
      },
      {
        "step": 4,
        "train_loss": 0.3607245683670044,
        "param_loss": 0.3607245683670044,
        "tau0_loss": 0.11875252425670624,
        "cfo_loss": 0.023664863780140877,
        "delay_loss": 0.19184935092926025,
        "doppler_loss": 0.007996538653969765,
        "rx_offset_loss": 0.01846131682395935,
        "channel_nmse": 414093.75,
        "channel_nmse_db": 56.17098675658148,
        "observed_symbol_nmse": 0.016492484137415886,
        "observed_symbol_nmse_db": -17.827139249283807,
        "val_channel_nmse": 414093.75,
        "val_channel_nmse_db": 56.17098675658148,
        "val_observed_symbol_nmse": 0.016492484137415886,
        "val_observed_symbol_nmse_db": -17.827139249283807
      },
      {
        "step": 5,
        "train_loss": 0.3111521005630493,
        "param_loss": 0.3111521005630493,
        "tau0_loss": 0.08254948258399963,
        "cfo_loss": 0.017609326168894768,
        "delay_loss": 0.18767233192920685,
        "doppler_loss": 0.007116763386875391,
        "rx_offset_loss": 0.016204196959733963
      },
      {
        "step": 6,
        "train_loss": 0.3132140040397644,
        "param_loss": 0.3132140040397644,
        "tau0_loss": 0.09745518863201141,
        "cfo_loss": 0.008341215550899506,
        "delay_loss": 0.18422572314739227,
        "doppler_loss": 0.005740114953368902,
        "rx_offset_loss": 0.017451748251914978
      },
      {
        "step": 7,
        "train_loss": 0.26999592781066895,
        "param_loss": 0.26999592781066895,
        "tau0_loss": 0.06406169384717941,
        "cfo_loss": 0.0019738583359867334,
        "delay_loss": 0.17919762432575226,
        "doppler_loss": 0.004922199063003063,
        "rx_offset_loss": 0.019840547814965248
      },
      {
        "step": 8,
        "train_loss": 0.2738359570503235,
        "param_loss": 0.2738359570503235,
        "tau0_loss": 0.07618892192840576,
        "cfo_loss": 0.0007424576906487346,
        "delay_loss": 0.17502760887145996,
        "doppler_loss": 0.003934716340154409,
        "rx_offset_loss": 0.017942236736416817
      },
      {
        "step": 9,
        "train_loss": 0.24294161796569824,
        "param_loss": 0.24294161796569824,
        "tau0_loss": 0.04638761281967163,
        "cfo_loss": 0.003466498339548707,
        "delay_loss": 0.1699768304824829,
        "doppler_loss": 0.0031909227836877108,
        "rx_offset_loss": 0.0199197456240654,
        "channel_nmse": 65219.671875,
        "channel_nmse_db": 48.14378609507728,
        "observed_symbol_nmse": 0.008258089423179626,
        "observed_symbol_nmse_db": -20.831204186013643,
        "val_channel_nmse": 65219.671875,
        "val_channel_nmse_db": 48.14378609507728,
        "val_observed_symbol_nmse": 0.008258089423179626,
        "val_observed_symbol_nmse_db": -20.831204186013643
      },
      {
        "step": 10,
        "train_loss": 0.2468346357345581,
        "param_loss": 0.2468346357345581,
        "tau0_loss": 0.05623671039938927,
        "cfo_loss": 0.006515691056847572,
        "delay_loss": 0.16562528908252716,
        "doppler_loss": 0.0026358168106526136,
        "rx_offset_loss": 0.01582111418247223
      },
      {
        "step": 11,
        "train_loss": 0.2198667675256729,
        "param_loss": 0.2198667675256729,
        "tau0_loss": 0.03168926388025284,
        "cfo_loss": 0.006852172315120697,
        "delay_loss": 0.1608957201242447,
        "doppler_loss": 0.002049455652013421,
        "rx_offset_loss": 0.018380146473646164
      },
      {
        "step": 12,
        "train_loss": 0.22009307146072388,
        "param_loss": 0.22009307146072388,
        "tau0_loss": 0.040296345949172974,
        "cfo_loss": 0.0059155188500881195,
        "delay_loss": 0.15643315017223358,
        "doppler_loss": 0.0018635682063177228,
        "rx_offset_loss": 0.015584481880068779
      },
      {
        "step": 13,
        "train_loss": 0.19767972826957703,
        "param_loss": 0.19767972826957703,
        "tau0_loss": 0.021208036690950394,
        "cfo_loss": 0.0030260237399488688,
        "delay_loss": 0.1519247442483902,
        "doppler_loss": 0.001484971377067268,
        "rx_offset_loss": 0.02003595605492592
      },
      {
        "step": 14,
        "train_loss": 0.19728399813175201,
        "param_loss": 0.19728399813175201,
        "tau0_loss": 0.029064945876598358,
        "cfo_loss": 0.0013325464678928256,
        "delay_loss": 0.14707615971565247,
        "doppler_loss": 0.0015653761802241206,
        "rx_offset_loss": 0.018244966864585876,
        "channel_nmse": 4740.345703125,
        "channel_nmse_db": 36.75810014983125,
        "observed_symbol_nmse": 0.0022126708645373583,
        "observed_symbol_nmse_db": -26.550831825081914,
        "val_channel_nmse": 4740.345703125,
        "val_channel_nmse_db": 36.75810014983125,
        "val_observed_symbol_nmse": 0.0022126708645373583,
        "val_observed_symbol_nmse_db": -26.550831825081914
      },
      {
        "step": 15,
        "train_loss": 0.18118812143802643,
        "param_loss": 0.18118812143802643,
        "tau0_loss": 0.01449755858629942,
        "cfo_loss": 0.0006123882485553622,
        "delay_loss": 0.14240320026874542,
        "doppler_loss": 0.0014004759723320603,
        "rx_offset_loss": 0.022274505347013474
      },
      {
        "step": 16,
        "train_loss": 0.17982734739780426,
        "param_loss": 0.17982734739780426,
        "tau0_loss": 0.021751217544078827,
        "cfo_loss": 0.0007404665811918676,
        "delay_loss": 0.13683724403381348,
        "doppler_loss": 0.0016586758429184556,
        "rx_offset_loss": 0.018839752301573753
      },
      {
        "step": 17,
        "train_loss": 0.16646084189414978,
        "param_loss": 0.16646084189414978,
        "tau0_loss": 0.010460445657372475,
        "cfo_loss": 0.0016287195030599833,
        "delay_loss": 0.13166235387325287,
        "doppler_loss": 0.0016879462637007236,
        "rx_offset_loss": 0.02102137729525566
      },
      {
        "step": 18,
        "train_loss": 0.16183620691299438,
        "param_loss": 0.16183620691299438,
        "tau0_loss": 0.017102401703596115,
        "cfo_loss": 0.0012329360470175743,
        "delay_loss": 0.12537400424480438,
        "doppler_loss": 0.00208279094658792,
        "rx_offset_loss": 0.01604405790567398
      },
      {
        "step": 19,
        "train_loss": 0.14930301904678345,
        "param_loss": 0.14930301904678345,
        "tau0_loss": 0.007975980639457703,
        "cfo_loss": 0.0011543617583811283,
        "delay_loss": 0.11972429603338242,
        "doppler_loss": 0.0022064789664000273,
        "rx_offset_loss": 0.018241915851831436,
        "channel_nmse": 4654.88232421875,
        "channel_nmse_db": 36.67908706458408,
        "observed_symbol_nmse": 0.0002843268739525229,
        "observed_symbol_nmse_db": -35.461820882801696,
        "val_channel_nmse": 4654.88232421875,
        "val_channel_nmse_db": 36.67908706458408,
        "val_observed_symbol_nmse": 0.0002843268739525229,
        "val_observed_symbol_nmse_db": -35.461820882801696
      },
      {
        "step": 20,
        "train_loss": 0.14406879246234894,
        "param_loss": 0.14406879246234894,
        "tau0_loss": 0.013955957256257534,
        "cfo_loss": 0.0004580774693749845,
        "delay_loss": 0.11309888958930969,
        "doppler_loss": 0.002580315573140979,
        "rx_offset_loss": 0.01397554762661457
      },
      {
        "step": 21,
        "train_loss": 0.1339145004749298,
        "param_loss": 0.1339145004749298,
        "tau0_loss": 0.006283337250351906,
        "cfo_loss": 0.0003982862690463662,
        "delay_loss": 0.10727769881486893,
        "doppler_loss": 0.002556050894781947,
        "rx_offset_loss": 0.0173991397023201
      },
      {
        "step": 22,
        "train_loss": 0.1299646496772766,
        "param_loss": 0.1299646496772766,
        "tau0_loss": 0.01151849702000618,
        "cfo_loss": 0.0007363365730270743,
        "delay_loss": 0.1007227897644043,
        "doppler_loss": 0.002665223553776741,
        "rx_offset_loss": 0.014321811497211456
      },
      {
        "step": 23,
        "train_loss": 0.12082040309906006,
        "param_loss": 0.12082040309906006,
        "tau0_loss": 0.004983191378414631,
        "cfo_loss": 0.0007941387011669576,
        "delay_loss": 0.09503192454576492,
        "doppler_loss": 0.002326350659132004,
        "rx_offset_loss": 0.017684802412986755
      },
      {
        "step": 24,
        "train_loss": 0.11608386039733887,
        "param_loss": 0.11608386039733887,
        "tau0_loss": 0.009432630613446236,
        "cfo_loss": 0.0009859236888587475,
        "delay_loss": 0.0887276902794838,
        "doppler_loss": 0.0021619542967528105,
        "rx_offset_loss": 0.014775658026337624,
        "channel_nmse": 78.4371109008789,
        "channel_nmse_db": 18.945215887831893,
        "observed_symbol_nmse": 2.6568259272607975e-05,
        "observed_symbol_nmse_db": -45.756368828777624,
        "val_channel_nmse": 78.4371109008789,
        "val_channel_nmse_db": 18.945215887831893,
        "val_observed_symbol_nmse": 2.6568259272607975e-05,
        "val_observed_symbol_nmse_db": -45.756368828777624
      }
    ],
    "final": {
      "step": 24,
      "train_loss": 0.11608386039733887,
      "param_loss": 0.11608386039733887,
      "tau0_loss": 0.009432630613446236,
      "cfo_loss": 0.0009859236888587475,
      "delay_loss": 0.0887276902794838,
      "doppler_loss": 0.0021619542967528105,
      "rx_offset_loss": 0.014775658026337624,
      "channel_nmse": 78.4371109008789,
      "channel_nmse_db": 18.945215887831893,
      "observed_symbol_nmse": 2.6568259272607975e-05,
      "observed_symbol_nmse_db": -45.756368828777624,
      "val_channel_nmse": 78.4371109008789,
      "val_channel_nmse_db": 18.945215887831893,
      "val_observed_symbol_nmse": 2.6568259272607975e-05,
      "val_observed_symbol_nmse_db": -45.756368828777624
    }
  }
]